setup.cfg
setup.py
dynamite/__init__.py
dynamite/config.py
dynamite/connection.py
dynamite/defines.py
dynamite/fields.py
dynamite/items.py
dynamite/models.py
dynamite/patterns.py
dynamite/schema.py
dynamite/tables.py
dynamite/test.py
dynamite/utils.py
dynamite.egg-info/PKG-INFO
dynamite.egg-info/SOURCES.txt
dynamite.egg-info/dependency_links.txt
dynamite.egg-info/requires.txt
dynamite.egg-info/top_level.txt