Metadata-Version: 1.1
Name: dynamite
Version: 0.7.0
Summary: Dynamite ORM
Home-page: https://github.com/viatoriche/dynamite
Author: viatoriche
Author-email: maxim@via-net.org
License: MIT
Download-URL: https://github.com/viatoriche/dynamite/tarball/0.7.0
Platform: UNKNOWN
